hicstraw.cpython-39-darwin.so
hic_straw-1.3.1.dist-info/METADATA
hic_straw-1.3.1.dist-info/WHEEL
hic_straw-1.3.1.dist-info/top_level.txt
hic_straw-1.3.1.dist-info/RECORD
