Metadata-Version: 2.1
Name: hic-straw
Version: 1.3.1
Summary: Straw bound with pybind11
Home-page: https://github.com/aidenlab/straw
Author: Neva C. Durand, Muhammad S Shamim
Author-email: neva@broadinstitute.org
License: MIT
Keywords: Hi-C,3D Genomics,Chromatin,ML
Platform: UNKNOWN
Requires-Python: >3.3
Requires-Dist: pybind11 (>=2.4)
